ocks/__init__.py
ocks/ssd1306.py
ocks-0.6.dist-info/LICENSE
ocks-0.6.dist-info/METADATA
ocks-0.6.dist-info/WHEEL
ocks-0.6.dist-info/top_level.txt
ocks-0.6.dist-info/RECORD
