Metadata-Version: 2.1
Name: ocks
Version: 0.6
Summary: Version 0.6 of the library has added a rotation feature.
Author: Cesar
Author-email: cesar.bautista@uelectronics.com
License: MIT License
License-File: LICENSE
